universalinit/__init__.py
universalinit/cli.py
universalinit/common/backup_db.sh
universalinit/common/db_visualizer/package.json
universalinit/common/db_visualizer/public/index.html
universalinit/common/db_visualizer/server.js
universalinit/common/restore_db.sh
universalinit/templateconfig.py
universalinit/templates/android/.gitignore
universalinit/templates/android/config.yml
universalinit/templates/android/init_script.sh
universalinit/templates/androidtv/config.yml
universalinit/templates/androidtv/init_script.sh
universalinit/templates/angular/.editorconfig
universalinit/templates/angular/.gitignore
universalinit/templates/angular/README.md
universalinit/templates/angular/angular.json
universalinit/templates/angular/config.yml
universalinit/templates/angular/eslint.config.mjs
universalinit/templates/angular/package-lock.json
universalinit/templates/angular/package.json
universalinit/templates/angular/public/favicon.ico
universalinit/templates/angular/src/app/app.component.css
universalinit/templates/angular/src/app/app.component.html
universalinit/templates/angular/src/app/app.component.spec.ts
universalinit/templates/angular/src/app/app.component.ts
universalinit/templates/angular/src/app/app.config.server.ts
universalinit/templates/angular/src/app/app.config.ts
universalinit/templates/angular/src/app/app.routes.ts
universalinit/templates/angular/src/index.html
universalinit/templates/angular/src/main.server.ts
universalinit/templates/angular/src/main.ts
universalinit/templates/angular/src/server.ts
universalinit/templates/angular/src/styles.css
universalinit/templates/angular/tsconfig.app.json
universalinit/templates/angular/tsconfig.json
universalinit/templates/angular/tsconfig.spec.json
universalinit/templates/astro/.gitignore
universalinit/templates/astro/README.md
universalinit/templates/astro/astro.config.mjs
universalinit/templates/astro/config.yml
universalinit/templates/astro/eslint.config.mjs
universalinit/templates/astro/package.json
universalinit-0.1.100.dist-info/METADATA
universalinit-0.1.100.dist-info/WHEEL
universalinit-0.1.100.dist-info/entry_points.txt
universalinit-0.1.100.dist-info/licenses/LICENSE
universalinit-0.1.100.dist-info/RECORD
