Metadata-Version: 2.4
Name: universalinit
Version: 0.1.100
Summary: 
License-File: LICENSE
Author: Zoltan Kuscsik
Author-email: zoltan@s57.io
Requires-Python: >=3.11
Classifier: Programming Language :: Python :: 3
Classifier: Programming Language :: Python :: 3.11
Classifier: Programming Language :: Python :: 3.12
Classifier: Programming Language :: Python :: 3.13
Classifier: Programming Language :: Python :: 3.14
Requires-Dist: PyYAML
Requires-Dist: pytest (>=8.3.4,<9.0.0)
Requires-Dist: universalinit-env (>=0.1.8,<0.2.0)
